MANIFEST.in
README.txt
setup.py
docs/HISTORY.txt
docs/LICENSE.txt
src/silva/__init__.py
src/silva.pas.membership.egg-info/PKG-INFO
src/silva.pas.membership.egg-info/SOURCES.txt
src/silva.pas.membership.egg-info/dependency_links.txt
src/silva.pas.membership.egg-info/namespace_packages.txt
src/silva.pas.membership.egg-info/not-zip-safe
src/silva.pas.membership.egg-info/requires.txt
src/silva.pas.membership.egg-info/top_level.txt
src/silva/pas/__init__.py
src/silva/pas/membership/__init__.py
src/silva/pas/membership/configure.zcml
src/silva/pas/membership/version.txt
src/silva/pas/membership/plugins/__init__.py
src/silva/pas/membership/plugins/membership.py
src/silva/pas/membership/www/members.png
src/silva/pas/membership/www/membershipAddForm.zpt