Metadata-Version: 1.1
Name: silva.pas.membership
Version: 1.2
Summary: Retrieve Silva membership information in PAS
Home-page: https://github.com/silvacms/silva.pas.membership
Author: Sylvain Viollon
Author-email: info@infrae.com
License: BSD
Keywords: silva pas membership
Platform: UNKNOWN
Classifier: Framework :: Zope2
Classifier: Programming Language :: Python
Classifier: Topic :: Software Development :: Libraries :: Python Modules
Classifier: License :: OSI Approved :: BSD License
